<?xml version="1.0" encoding="UTF-8"?>
<objects serializationModel="Studio.02.02.00">
	<object class="EncodingSetting" id="{0c85e869-9e6f-4b7a-a58a-43652008c024}">
		<property name="encodingFormat">
			<value>3</value>
		</property>
		<property name="quality">
			<value>37</value>
		</property>
		<relationship name="platform">
			<destination>{4b96dc90-1a0d-49b6-8682-df873b2add64}</destination>
		</relationship>
		<relationship name="encodable">
			<destination>{f54a15df-6569-480b-8364-763b3bc099a9}</destination>
		</relationship>
	</object>
</objects>
